cztranslator/Happynow.py
cztranslator/__init__.py
cztranslator-0.0.6.dist-info/LICENSE
cztranslator-0.0.6.dist-info/METADATA
cztranslator-0.0.6.dist-info/WHEEL
cztranslator-0.0.6.dist-info/top_level.txt
cztranslator-0.0.6.dist-info/RECORD
