Metadata-Version: 2.1
Name: cztranslator
Version: 0.0.6
Summary: cztranslator
Home-page: https://github.com/WencaiZheng
Author: Noven Zheng
Author-email: wz1298@nyu.edu
License: MIT License
Keywords: cztranslator
Platform: any
